fastapi_extra/__init__.py
fastapi_extra/_patch.py
fastapi_extra/cursor.cp312-win_amd64.pyd
fastapi_extra/cursor.pyi
fastapi_extra/dependency.py
fastapi_extra/form.py
fastapi_extra/py.typed
fastapi_extra/response.py
fastapi_extra/routing.cp312-win_amd64.pyd
fastapi_extra/routing.pyi
fastapi_extra/settings.py
fastapi_extra/types.py
fastapi_extra/urlparse.cp312-win_amd64.pyd
fastapi_extra/urlparse.pyi
fastapi_extra/utils.py
fastapi_extra/cache/__init__.py
fastapi_extra/cache/redis.py
fastapi_extra/database/__init__.py
fastapi_extra/database/model.py
fastapi_extra/database/service.py
fastapi_extra/database/session.py
fastapi_extra/native/cursor.pyx
fastapi_extra/native/routing.pyx
fastapi_extra/native/urlparse.pyx
fastapi_extra-0.3.0.dist-info/licenses/LICENSE
fastapi_extra-0.3.0.dist-info/METADATA
fastapi_extra-0.3.0.dist-info/WHEEL
fastapi_extra-0.3.0.dist-info/top_level.txt
fastapi_extra-0.3.0.dist-info/RECORD
