Metadata-Version: 2.4
Name: fastapi-extra
Version: 0.3.0
Summary: extra package for fastapi.
Author-email: Ziyan Yin <408856732@qq.com>
License: BSD-3-Clause
Classifier: Development Status :: 4 - Beta
Classifier: Environment :: Web Environment
Classifier: Intended Audience :: Developers
Classifier: License :: OSI Approved :: BSD License
Classifier: Operating System :: OS Independent
Classifier: Programming Language :: Python :: 3 :: Only
Classifier: Programming Language :: Python :: 3.12
Classifier: Programming Language :: Python :: Implementation :: CPython
Classifier: Topic :: Internet
Classifier: Topic :: Software Development :: Libraries :: Application Frameworks
Classifier: Topic :: Software Development :: Libraries :: Python Modules
Requires-Python: >=3.12
License-File: LICENSE
Requires-Dist: fastapi<0.129.0,>=0.128.0
Requires-Dist: httpx<0.29.0,>=0.28.0
Requires-Dist: pydantic-settings>=2.12.0
Requires-Dist: sqlmodel>=0.0.22
Provides-Extra: redis
Requires-Dist: redis; extra == "redis"
Provides-Extra: scheduler
Requires-Dist: apscheduler; extra == "scheduler"
Provides-Extra: mysql
Requires-Dist: asyncmy; extra == "mysql"
Provides-Extra: pgsql
Requires-Dist: asyncpg; extra == "pgsql"
Provides-Extra: aiomysql
Requires-Dist: aiomysql; extra == "aiomysql"
Dynamic: license-file
